cryptoco_py/__init__.py
cryptoco_py/__main__.py
cryptoco_py-0.1.7.dist-info/entry_points.txt
cryptoco_py-0.1.7.dist-info/WHEEL
cryptoco_py-0.1.7.dist-info/METADATA
cryptoco_py-0.1.7.dist-info/RECORD
