Metadata-Version: 2.1
Name: cryptoco-py
Version: 0.1.7
Summary: A package to query cryptocurrency information
Home-page: https://github.com/Edmain1/CryptoCo-py
License: MIT
Author: Jawad Abduljawad(TerminalJ)
Author-email: jawadhamdiabduljawad@gmail.com
Requires-Python: >=3,<4
Classifier: License :: OSI Approved :: MIT License
Classifier: Programming Language :: Python :: 3
Classifier: Programming Language :: Python :: 3.10
Classifier: Programming Language :: Python :: 3.4
Classifier: Programming Language :: Python :: 3.5
Classifier: Programming Language :: Python :: 3.6
Classifier: Programming Language :: Python :: 3.7
Classifier: Programming Language :: Python :: 3.8
Classifier: Programming Language :: Python :: 3.9
Requires-Dist: requests (>=2.26.0,<3.0.0)
Requires-Dist: typer[all] (>=0.4.0,<0.5.0)
Project-URL: Repository, https://github.com/Edmain1/CryptoCo-py
